ripe_ip_search.py
ripe_ip_search-0.2.0.dist-info/LICENSE
ripe_ip_search-0.2.0.dist-info/METADATA
ripe_ip_search-0.2.0.dist-info/WHEEL
ripe_ip_search-0.2.0.dist-info/entry_points.txt
ripe_ip_search-0.2.0.dist-info/top_level.txt
ripe_ip_search-0.2.0.dist-info/RECORD
