Metadata-Version: 2.1
Name: ripe_ip_search
Version: 0.2.0
Author: Sergey M
License: Apache License
Project-URL: Repository, https://github.com/s3rgeym/ripe-ip-search.git
Classifier: License :: OSI Approved :: Apache Software License
Classifier: Topic :: Internet
Requires-Python: >=3.11.7
License-File: LICENSE
Requires-Dist: requests
Provides-Extra: dev
Requires-Dist: black ; extra == 'dev'
Requires-Dist: pylint ; extra == 'dev'
Provides-Extra: test
Requires-Dist: pytest ; extra == 'test'
